LICENSE
MANIFEST.in
README.md
VERSION
classifiers.txt
compare.png
requirements.txt
setup.py
scipolate/__init__.py
scipolate/_helper.py
scipolate/idw.py
scipolate/main.py
scipolate/methods.py
scipolate.egg-info/PKG-INFO
scipolate.egg-info/SOURCES.txt
scipolate.egg-info/dependency_links.txt
scipolate.egg-info/not-zip-safe
scipolate.egg-info/top_level.txt