Metadata-Version: 2.1
Name: scipolate
Version: 0.1.3
Summary: helper for running different scipy 2D interpolations
Home-page: UNKNOWN
Author: Mirko Maelicke
Author-email: mirko.maelicke@kit.edu
License: GNU 3.0
Platform: UNKNOWN
Classifier: Development Status :: 4 - Beta
Classifier: Intended Audience :: Science/Research
Classifier: License :: OSI Approved :: GNU General Public License v3 (GPLv3)
Classifier: Natural Language :: English
Classifier: Programming Language :: Python :: 3.7
Classifier: Topic :: Scientific/Engineering :: Information Analysis
Classifier: Topic :: Scientific/Engineering :: GIS
Classifier: Topic :: Scientific/Engineering :: Visualization
